salesvision/__init__.py
salesvision/client_database.py
salesvision/image_utils.py
salesvision/metrics.py
salesvision/server_estimation.py
salesvision/visualization.py
salesvision-0.1.6.dist-info/LICENSE
salesvision-0.1.6.dist-info/METADATA
salesvision-0.1.6.dist-info/WHEEL
salesvision-0.1.6.dist-info/top_level.txt
salesvision-0.1.6.dist-info/RECORD
