Metadata-Version: 2.1
Name: salesvision
Version: 0.1.6
Summary: Salesvision provides accurate, reliable and scalable fashion image analysis
Home-page: https://github.com/pypa/sampleproject
Author: broutonlab
Author-email: poltavsky@broutonlab.com
License: UNKNOWN
Platform: UNKNOWN
Classifier: Programming Language :: Python :: 3
Classifier: License :: OSI Approved :: MIT License
Classifier: Operating System :: OS Independent
Requires-Python: >=3.6
Requires-Dist: imagehash
Requires-Dist: numpy
Requires-Dist: pymongo
Requires-Dist: requests
Requires-Dist: pillow
Requires-Dist: opencv-python
